nn_tuning/__init__.py
nn_tuning/fitting_manager.py
nn_tuning/input_manager.py
nn_tuning/output_manager.py
nn_tuning/plot.py
nn_tuning/statistics_helper.py
nn_tuning/networks/__init__.py
nn_tuning/networks/alexnet.py
nn_tuning/networks/network.py
nn_tuning/networks/prednet.py
nn_tuning/stimulus_generator/__init__.py
nn_tuning/stimulus_generator/numerosity_stimulus_generator.py
nn_tuning/stimulus_generator/prf_stimulus_generator.py
nn_tuning/stimulus_generator/stimulus_generator.py
nn_tuning/stimulus_generator/two_d_stimulus_generator.py
nn_tuning/storage/__init__.py
nn_tuning/storage/database.py
nn_tuning/storage/error.py
nn_tuning/storage/helpers.py
nn_tuning/storage/storage_manager.py
nn_tuning/storage/table.py
nn_tuning/storage/table_set.py
prednet/__init__.py
prednet/data_utils.py
prednet/keras_utils.py
prednet/kitti_evaluate.py
prednet/kitti_extrap_finetune.py
prednet/kitti_settings.py
prednet/kitti_train.py
prednet/numerosity_generator.py
prednet/prednet.py
prednet/process_kitti.py
prednet/tensorflow_help_functions.py
nn_tuning_prednet-1.0.2.dist-info/METADATA
nn_tuning_prednet-1.0.2.dist-info/WHEEL
nn_tuning_prednet-1.0.2.dist-info/top_level.txt
nn_tuning_prednet-1.0.2.dist-info/RECORD
