Metadata-Version: 2.1
Name: nn-tuning-prednet
Version: 1.0.2
Summary: Analyse the tuning functions of neurons in artificial neural networks
Home-page: https://github.com/nn-analysis/nn_tuning
Author: Jesca Hoogendijk
Author-email: j.hoogendijk@uu.nl
License: GNU LGPLv3
Project-URL: Documentation, https://nn-analysis.github.io/nn_tuning/nn_tuning.html
Platform: UNKNOWN
Classifier: License :: OSI Approved :: GNU Lesser General Public License v3 (LGPLv3)
Classifier: Programming Language :: Python
Classifier: Programming Language :: Python :: 3
Classifier: Operating System :: OS Independent
Requires-Python: >=3.6, <3.7
Requires-Dist: numpy
Requires-Dist: tqdm
Requires-Dist: Pillow
Requires-Dist: tensorflow-gpu (==1.14.0)
